[{"ID_song": "0", "username": "iamgide", "nameSong": "testOutput0", "mood": "Sad", "path": "../frontend/static/fileSong/testOutput0.mid", "duration": "15"}, {"ID_song": "1", "username": "iamgide", "nameSong": "testOutput1", "mood": "Happy", "path": "../frontend/static/fileSong/testOutput1.mid", "duration": "20"}, {"ID_song": "2", "username": "lnw", "nameSong": "testOutput2", "mood": "Relax", "path": "../frontend/static/fileSong/testOutput2.mid", "duration": "20"}, {"ID_song": "4", "username": "iamgide", "nameSong": "testOutput4", "mood": "Sad", "path": "../frontend/static/fileSong/testOutput4.mid", "duration": "20"}, {"ID_song": "5", "username": "lnw", "nameSong": "testOutput5", "mood": "Sad", "path": "../frontend/static/fileSong/testOutput5.mid", "duration": "20"}, {"ID_song": "5", "username": "admin", "nameSong": "BestOfrelax1", "mood": "Relax", "path": "../frontend/static/fileSong/BestOfrelax1.mid", "duration": "28"}, {"ID_song": "6", "username": "admin", "nameSong": "BestOfrelax2", "mood": "Relax", "path": "../frontend/static/fileSong/BestOfrelax2.mid", "duration": "24"}, {"ID_song": "7", "username": "admin", "nameSong": "BestOfsad1", "mood": "Sad", "path": "../frontend/static/fileSong/BestOfsad1.mid", "duration": "46"}, {"ID_song": "8", "username": "admin", "nameSong": "BestOfsad2", "mood": "Sad", "path": "../frontend/static/fileSong/BestOfsad2.mid", "duration": "42"}, {"ID_song": "10", "username": "userTester", "nameSong": "testOutput10", "mood": "Happy", "path": "../frontend/static/fileSong/testOutput10.mid", "duration": "20"}, {"ID_song": "11", "username": "userTester", "nameSong": "testOutput11", "mood": "Sad", "path": "../frontend/static/fileSong/testOutput11.mid", "duration": "20"}, {"ID_song": "12", "username": "userTester", "nameSong": "testOutput12", "mood": "Relax", "path": "../frontend/static/fileSong/testOutput12.mid", "duration": "20"}, {"ID_song": "13", "username": "userTester", "nameSong": "testOutput13", "mood": "Happy", "path": "../frontend/static/fileSong/testOutput13.mid", "duration": "20"}, {"ID_song": "14", "username": "userTester", "nameSong": "testOutput14", "mood": "Relax", "path": "../frontend/static/fileSong/testOutput14.mid", "duration": "20"}, {"ID_song": "15", "username": "userTester", "nameSong": "testOutput15", "mood": "Happy", "path": "../frontend/static/fileSong/testOutput15.mid", "duration": "20"}, {"ID_song": "16", "username": "userTester", "nameSong": "testOutput16", "mood": "Happy", "path": "../frontend/static/fileSong/testOutput16.mid", "duration": "20"}, {"ID_song": "17", "username": "userTester", "nameSong": "testOutput17", "mood": "Relax", "path": "../frontend/static/fileSong/testOutput17.mid", "duration": "20"}, {"ID_song": "18", "username": "userTester", "nameSong": "testOutput18", "mood": "Happy", "path": "../frontend/static/fileSong/testOutput18.mid", "duration": "20"}, {"ID_song": "19", "username": "userTester", "nameSong": "testOutput19", "mood": "Happy", "path": "../frontend/static/fileSong/testOutput19.mid", "duration": "20"}, {"ID_song": "20", "username": "userTester", "nameSong": "testOutput20", "mood": "Relax", "path": "../frontend/static/fileSong/testOutput20.mid", "duration": "20"}, {"ID_song": "21", "username": "userTester", "nameSong": "testOutput21", "mood": "Happy", "path": "../frontend/static/fileSong/testOutput21.mid", "duration": "20"}, {"ID_song": "22", "username": "userTester", "nameSong": "testOutput22", "mood": "Happy", "path": "../frontend/static/fileSong/testOutput22.mid", "duration": "20"}, {"ID_song": "23", "username": "userTester", "nameSong": "testOutput23", "mood": "Happy", "path": "../frontend/static/fileSong/testOutput23.mid", "duration": "20"}, {"ID_song": "24", "username": "userTester", "nameSong": "testOutput24", "mood": "Sad", "path": "../frontend/static/fileSong/testOutput24.mid", "duration": "20"}, {"ID_song": "25", "username": "userTester", "nameSong": "testOutput25", "mood": "Sad", "path": "../frontend/static/fileSong/testOutput25.mid", "duration": "20"}, {"ID_song": "26", "username": "userTester", "nameSong": "testOutput26", "mood": "Happy", "path": "../frontend/static/fileSong/testOutput26.mid", "duration": "20"}, {"ID_song": "27", "username": "userTester", "nameSong": "testOutput27", "mood": "Happy", "path": "../frontend/static/fileSong/testOutput27.mid", "duration": "20"}, {"ID_song": "28", "username": "userTester", "nameSong": "testOutput28", "mood": "Sad", "path": "../frontend/static/fileSong/testOutput28.mid", "duration": "20"}, {"ID_song": "29", "username": "userTester", "nameSong": "testOutput29", "mood": "Happy", "path": "../frontend/static/fileSong/testOutput29.mid", "duration": "10"}, {"ID_song": "30", "username": "userTester", "nameSong": "testOutput30", "mood": "Happy", "path": "../frontend/static/fileSong/testOutput30.mid", "duration": "20"}, {"ID_song": "31", "username": "userTester", "nameSong": "testOutput31", "mood": "Happy", "path": "../frontend/static/fileSong/testOutput31.mid", "duration": "20"}, {"ID_song": "32", "username": "userTester", "nameSong": "testOutput32", "mood": "Happy", "path": "../frontend/static/fileSong/testOutput32.mid", "duration": "20"}, {"ID_song": "33", "username": "userTester", "nameSong": "testOutput33", "mood": "Happy", "path": "../frontend/static/fileSong/testOutput33.mid", "duration": "20"}, {"ID_song": "34", "username": "userTester", "nameSong": "testOutput34", "mood": "Happy", "path": "../frontend/static/fileSong/testOutput34.mid", "duration": "20"}, {"ID_song": "35", "username": "userTester", "nameSong": "testOutput35", "mood": "Happy", "path": "../frontend/static/fileSong/testOutput35.mid", "duration": "20"}, {"ID_song": "36", "username": "userTester", "nameSong": "testOutput36", "mood": "Happy", "path": "../frontend/static/fileSong/testOutput36.mid", "duration": "20"}, {"ID_song": "37", "username": "userTester", "nameSong": "testOutput37", "mood": "Happy", "path": "../frontend/static/fileSong/testOutput37.mid", "duration": "20"}, {"ID_song": "38", "username": "userTester", "nameSong": "testOutput38", "mood": "Happy", "path": "../frontend/static/fileSong/testOutput38.mid", "duration": 5}, {"ID_song": "39", "username": "userTester", "nameSong": "testOutput39", "mood": "Happy", "path": "../frontend/static/fileSong/testOutput39.mid", "duration": "20"}, {"ID_song": "40", "username": "userTester", "nameSong": "testOutput40", "mood": "Happy", "path": "../frontend/static/fileSong/testOutput40.mid", "duration": "20"}, {"ID_song": "41", "username": "userTester", "nameSong": "testOutput41", "mood": "Happy", "path": "../frontend/static/fileSong/testOutput41.mid", "duration": "20"}, {"ID_song": "42", "username": "userTester", "nameSong": "testOutput42", "mood": "Happy", "path": "../frontend/static/fileSong/testOutput42.mid", "duration": "20"}, {"ID_song": "43", "username": "userTester", "nameSong": "testOutput43", "mood": "Happy", "path": "../frontend/static/fileSong/testOutput43.mid", "duration": "20"}, {"ID_song": "44", "username": "userTester", "nameSong": "testOutput44", "mood": "Happy", "path": "../frontend/static/fileSong/testOutput44.mid", "duration": "20"}, {"ID_song": "45", "username": "userTester", "nameSong": "testOutput45", "mood": "Happy", "path": "../frontend/static/fileSong/testOutput45.mid", "duration": "20"}, {"ID_song": "46", "username": "userTester", "nameSong": "testOutput46", "mood": "Happy", "path": "../frontend/static/fileSong/testOutput46.mid", "duration": "20"}, {"ID_song": "47", "username": "userTester", "nameSong": "testOutput47", "mood": "Sad", "path": "../frontend/static/fileSong/testOutput47.mid", "duration": "20"}, {"ID_song": "48", "username": "userTester", "nameSong": "testOutput48", "mood": "Happy", "path": "../frontend/static/fileSong/testOutput48.mid", "duration": "20"}, {"ID_song": "49", "username": "userTester", "nameSong": "testOutput49", "mood": "Happy", "path": "../frontend/static/fileSong/testOutput49.mid", "duration": "20"}, {"ID_song": "50", "username": "userTester", "nameSong": "testOutput50", "mood": "Happy", "path": "../frontend/static/fileSong/testOutput50.mid", "duration": "20"}, {"ID_song": "51", "username": "userTester", "nameSong": "testOutput51", "mood": "Happy", "path": "../frontend/static/fileSong/testOutput51.mid", "duration": "20"}, {"ID_song": "52", "username": "userTester", "nameSong": "testOutput52", "mood": "Happy", "path": "../frontend/static/fileSong/testOutput52.mid", "duration": "20"}, {"ID_song": "53", "username": "userTester", "nameSong": "testOutput53", "mood": "Sad", "path": "../frontend/static/fileSong/testOutput53.mid", "duration": "20"}, {"ID_song": "54", "username": "userTester", "nameSong": "testOutput54", "mood": "Happy", "path": "../frontend/static/fileSong/testOutput54.mid", "duration": "20"}, {"ID_song": "55", "username": "userTester", "nameSong": "testOutput55", "mood": "Relax", "path": "../frontend/static/fileSong/testOutput55.mid", "duration": "20"}, {"ID_song": "56", "username": "userTester", "nameSong": "testOutput56", "mood": "Happy", "path": "../frontend/static/fileSong/testOutput56.mid", "duration": "20"}, {"ID_song": "57", "username": "userTester", "nameSong": "testOutput57", "mood": "Happy", "path": "../frontend/static/fileSong/testOutput57.mid", "duration": "20"}, {"ID_song": "58", "username": "userTester", "nameSong": "testOutput58", "mood": "Happy", "path": "../frontend/static/fileSong/testOutput58.mid", "duration": 5}, {"ID_song": "59", "username": "userTester", "nameSong": "testOutput59", "mood": "Happy", "path": "../frontend/static/fileSong/testOutput59.mid", "duration": "20"}]